{
  "frames": {
    "wreckage 0.aseprite": {
      "frame": {
        "x": 0,
        "y": 0,
        "w": 8,
        "h": 8
      },
      "rotated": false,
      "trimmed": false,
      "spriteSourceSize": {
        "x": 0,
        "y": 0,
        "w": 8,
        "h": 8
      },
      "sourceSize": {
        "w": 8,
        "h": 8
      },
      "duration": 100
    },
    "wreckage 1.aseprite": {
      "frame": {
        "x": 8,
        "y": 0,
        "w": 8,
        "h": 8
      },
      "rotated": false,
      "trimmed": false,
      "spriteSourceSize": {
        "x": 0,
        "y": 0,
        "w": 8,
        "h": 8
      },
      "sourceSize": {
        "w": 8,
        "h": 8
      },
      "duration": 100
    },
    "wreckage 2.aseprite": {
      "frame": {
        "x": 0,
        "y": 8,
        "w": 8,
        "h": 8
      },
      "rotated": false,
      "trimmed": false,
      "spriteSourceSize": {
        "x": 0,
        "y": 0,
        "w": 8,
        "h": 8
      },
      "sourceSize": {
        "w": 8,
        "h": 8
      },
      "duration": 100
    }
  },
  "meta": {
    "app": "http://www.aseprite.org/",
    "version": "1.2.9",
    "image": "/Users/david/workspace/libgdx/beat/core/assets/sheets/wreckage.png",
    "format": "RGBA8888",
    "size": {
      "w": 16,
      "h": 16
    },
    "scale": "1",
    "frameTags": [
    ],
    "slices": [
    ]
  }
}
